ksize/cli.py
ksize/kafka_install.py
ksize/kafka_topic_size.py
ksize-0.1.5.dist-info/METADATA
ksize-0.1.5.dist-info/WHEEL
ksize-0.1.5.dist-info/entry_points.txt
ksize-0.1.5.dist-info/RECORD
