Metadata-Version: 2.1
Name: ksize
Version: 0.1.5
Summary: 
Author: drunkensway
Author-email: alexanderrochette@gmail.com
Requires-Python: >=3.11,<4.0
Classifier: Programming Language :: Python :: 3
Classifier: Programming Language :: Python :: 3.11
Requires-Dist: click (>=8.1.7,<9.0.0)
